Metadata-Version: 1.0
Name: OneRule
Version: 0.0.3
Summary: One rule algorithm, Author orgnized according to llh_1178's csdn blog
Home-page: https://github.com/tengyuanyang/Onerule.git
Author: Dr Li
Author-email: 303984464@qq.com
License: MIT
Platform: UNKNOWN
